{
    "difficulty": "easy",
    "similarQuestions": [
        {
            "title": "Reverse Linked List II",
            "titleSlug": "reverse-linked-list-ii",
            "difficulty": "Medium",
            "translatedTitle": null
        },
        {
            "title": "Binary Tree Upside Down",
            "titleSlug": "binary-tree-upside-down",
            "difficulty": "Medium",
            "translatedTitle": null
        },
        {
            "title": "Palindrome Linked List",
            "titleSlug": "palindrome-linked-list",
            "difficulty": "Easy",
            "translatedTitle": null
        },
        {
            "title": "Reverse Nodes in Even Length Groups",
            "titleSlug": "reverse-nodes-in-even-length-groups",
            "difficulty": "Medium",
            "translatedTitle": null
        },
        {
            "title": "Maximum Twin Sum of a Linked List",
            "titleSlug": "maximum-twin-sum-of-a-linked-list",
            "difficulty": "Medium",
            "translatedTitle": null
        },
        {
            "title": "Remove Nodes From Linked List",
            "titleSlug": "remove-nodes-from-linked-list",
            "difficulty": "Medium",
            "translatedTitle": null
        },
        {
            "title": "Insert Greatest Common Divisors in Linked List",
            "titleSlug": "insert-greatest-common-divisors-in-linked-list",
            "difficulty": "Medium",
            "translatedTitle": null
        }
    ]
}